modulos_client/__init__.py
modulos_client/_client.py
modulos_client/_exceptions.py
modulos_client/_resource.py
modulos_client/_version.py
modulos_client/resources/__init__.py
modulos_client/resources/evidence/__init__.py
modulos_client/resources/evidence/evidence.py
modulos_client/resources/evidence/upload.py
modulos_client/resources/testing/__init__.py
modulos_client/resources/testing/logs.py
modulos_client/resources/testing/testing.py
modulos_client-1.0.4.dist-info/METADATA
modulos_client-1.0.4.dist-info/WHEEL
modulos_client-1.0.4.dist-info/entry_points.txt
modulos_client-1.0.4.dist-info/top_level.txt
modulos_client-1.0.4.dist-info/RECORD
