Metadata-Version: 2.2
Name: modulos_client
Version: 1.0.4
Summary: Package to interact with the Modulos Platform
Author-email: Modulos AG <contact@modulos.ai>
Project-URL: Homepage, https://github.com/Modulos/modulos_client
Project-URL: Bug Reports, https://github.com/Modulos/modulos_client/issues
Project-URL: Source, https://github.com/Modulos/modulos_client
Keywords: modulos_client
Classifier: Intended Audience :: Developers
Classifier: Natural Language :: English
Classifier: Programming Language :: Python :: 3.10
Classifier: Programming Language :: Python :: 3.11
Requires-Python: >=3.10
Requires-Dist: pandas<=2.2.3,>=1.5.3
Requires-Dist: pydantic<=2.12.0,>=2.4.2
Requires-Dist: requests<=2.33.0,>=2.0.0
Provides-Extra: dev
Requires-Dist: coverage==7.7.0; extra == "dev"
Requires-Dist: pytest<8.4.0,>=8.3.5; extra == "dev"
Requires-Dist: pyYAML<=6.0.2,>=6.0.1; extra == "dev"
Requires-Dist: tox==4.24.2; extra == "dev"
Requires-Dist: responses>=0.25.7; extra == "dev"
